Metadata-Version: 2.1
Name: mkdocs-material
Version: 4.6.3
Summary: A Material Design theme for MkDocs
Home-page: https://squidfunk.github.io/mkdocs-material/
Author: Martin Donath
Author-email: martin.donath@squidfunk.com
License: MIT
Keywords: mkdocs,documentation,theme
Platform: UNKNOWN
Classifier: Development Status :: 5 - Production/Stable
Classifier: License :: OSI Approved :: MIT License
Classifier: Programming Language :: JavaScript
Classifier: Programming Language :: Python
Classifier: Topic :: Documentation
Classifier: Topic :: Text Processing :: Markup :: HTML
